setup.cfg
setup.py
biolite/__init__.py
biolite/catalog.py
biolite/config.py
biolite/database.py
biolite/diagnostics.py
biolite/pipeline.py
biolite/report.py
biolite/utils.py
biolite/wrappers.py
biolite.egg-info/PKG-INFO
biolite.egg-info/SOURCES.txt
biolite.egg-info/dependency_links.txt
biolite.egg-info/requires.txt
biolite.egg-info/top_level.txt
biolite/config/biolite.cfg
biolite/data/SRA.common.xsd
biolite/data/SRA.experiment.xsd
biolite/data/SRA.run.xsd
biolite/data/SRA.sample.xsd
biolite/data/SRA.study.xsd
biolite/data/SRA.submission.xsd
biolite/data/bootstrap.min.css
biolite/data/d3.min.js
biolite/data/d3.phylogram.js
biolite/data/d3.v3.min.js
biolite/data/glyphicons-halflings-white.png
biolite/data/glyphicons-halflings.png
biolite/data/jquery.min.js
biolite/data/jsphylosvg-min.js
biolite/data/newick.js
biolite/data/raphael-min.js
biolite/data/tabular_report.html
biolite/workflows/__init__.py
biolite/workflows/assembly.py
biolite/workflows/blast.py
biolite/workflows/phylogeny.py
biolite/workflows/rrna.py
biolite/workflows/sra.py
biolite/workflows/transcriptome.py
scripts/bl-catalog
scripts/bl-diagnostics
scripts/bl-examl
scripts/bl-examl-bootstraps
scripts/bl-plot-tree
scripts/bl-sra
scripts/bl-treepruning